style50/__init__.py
style50/__main__.py
style50/_api.py
style50/languages.py
style50/renderer/__init__.py
style50/renderer/_renderers.py
style50/renderer/templates/results.html
style50-2.10.4.dist-info/LICENSE
style50-2.10.4.dist-info/METADATA
style50-2.10.4.dist-info/WHEEL
style50-2.10.4.dist-info/dependency_links.txt
style50-2.10.4.dist-info/entry_points.txt
style50-2.10.4.dist-info/top_level.txt
style50-2.10.4.dist-info/RECORD
