Metadata-Version: 2.1
Name: style50
Version: 2.10.4
Summary: This is style50, with which code can be checked against the CS50 style guide
Home-page: https://github.com/cs50/style50
Author: CS50
Author-email: sysadmins@cs50.harvard.edu
License: GPLv3
Keywords: style,style50
Classifier: Intended Audience :: Education
Classifier: Programming Language :: Python :: 3
Classifier: Topic :: Education
Classifier: Topic :: Utilities
License-File: LICENSE
Requires-Dist: autopep8>=2.1.0
Requires-Dist: clang-format>=18.1.2
Requires-Dist: icdiff
Requires-Dist: jsbeautifier
Requires-Dist: pycodestyle==2.12.0
Requires-Dist: python-magic
Requires-Dist: termcolor
Requires-Dist: jinja2>=2.10
